{"Vermont": {"lat": 44.5990718, "lng": -72.5002608}, "USVI": {"lat": 18.3356533, "lng": -64.956052}, "Costa Rica": {"lat": 10.2735633, "lng": -84.0739102}, "New Hampshire": {"lat": 43.4849133, "lng": -71.6553992}, "Nicaragua": {"lat": 12.6090157, "lng": -85.2936911}, "Guatemala": {"lat": 15.5855545, "lng": -90.345759}, "Washington State": {"lat": 47.2868352, "lng": -120.212613}, "California": {"lat": 36.7014631, "lng": -118.755997}, "BVI": {"lat": 19.229068, "lng": 72.8573628}, "Bali, Indonesia": {"lat": -8.2271303, "lng": 115.1919203}, "India": {"lat": 22.3511148, "lng": 78.6677428}, "South Africa": {"lat": -28.8166236, "lng": 24.991639}, "Puerto Rico": {"lat": 18.2247706, "lng": -66.4858295}, "New York": {"lat": 40.7127281, "lng": -74.0060152}, "Jay Peak, Vermont": {"lat": 44.9242294, "lng": -72.5256931}, "Rio Pacuare, Costa Rica": {"lat": 9.9428498, "lng": -83.5347444}, "Mt Washington, New Hampshire": {"lat": 44.2704946, "lng": -71.3033045}, "Cerro Chirripo, Costa Rica": {"lat": 9.4843073, "lng": -83.4885816}, "Volcan Concepcion, Nicaragua": {"lat": 11.5390087, "lng": -85.6225811}, "Olympic Hot Springs, Washington State": {"lat": 47.9765393, "lng": -123.6893553}, "Palisades Tahoe, California": {"lat": 39.19662245, "lng": -120.23454683218175}, "Menjangan Island, Bali, Indonesia": {"lat": -8.09601895, "lng": 114.51779643528896}, "Gunung Batur, Bali, Indonesia": {"lat": -8.2394154, "lng": 115.3779603}, "Manali, India": {"lat": 32.2454608, "lng": 77.1872926}, "Table Mountain, South Africa": {"lat": -33.959063513168815, "lng": 18.403871601688447}, "Mt Mansfield, Vermont": {"lat": 44.543947, "lng": -72.81431}, "Vieques, Puerto Rico": {"lat": 18.1215622, "lng": -65.45746403129988}, "Echo Lake, New York": {"lat": 42.09712075, "lng": -74.09098064426703}, "Volcan Tajumulco, Guatemala": {"lat": 15.0430989, "lng": -91.903608}, "Corcovado, Costa Rica": {"lat": 10.0615, "lng": -84.12489605}, "Haulover, Saint Thomas - Saint John District, United States Virgin Islands, United States": {"lat": 18.3506378, "lng": -64.6843396}, "Francis Bay Beach, Saint Thomas - Saint John District, United States Virgin Islands, United States": {"lat": 18.3648379, "lng": -64.7436297}, "Loblolly Bay, British Virgin Islands": {"lat": 18.7408432, "lng": -64.3102596}, "NaN": {"lat": 46.3144754, "lng": 11.0480288}, "Cabo Pulmo, Mexico": {"lat": 23.4453627, "lng": -109.4240213}, "Los Arbolitos, Municipio de Los Cabos, Baja California Sur, M\u00e9xico": {"lat": 23.4045736, "lng": -109.42544579648788}}